{"cameraMode":{"drawMode":0,"name":"Shaded","section":"Shading Mode"},"sceneLighting":false,"audioPlay":false,"sceneViewState":{"m_AlwaysRefresh":false,"showFog":true,"showSkybox":false,"showFlares":true,"showImageEffects":true,"showParticleSystems":true,"showVisualEffectGraphs":true,"m_FxEnabled":true},"in2DMode":false,"pivot":{"x":293.7554626464844,"y":384.2300109863281,"z":-23.083168029785158},"rotation":{"x":-0.3530871868133545,"y":0.00825459323823452,"z":-0.002884709043428302,"w":-0.9357535243034363},"size":2.1728785037994386,"orthographic":false}